timesheet_gitlab/__init__.py
timesheet_gitlab/timesheet_gitlab.py
timesheet_gitlab-1.0.1.data/scripts/timesheet_gitlab
timesheet_gitlab-1.0.1.dist-info/LICENSE
timesheet_gitlab-1.0.1.dist-info/METADATA
timesheet_gitlab-1.0.1.dist-info/WHEEL
timesheet_gitlab-1.0.1.dist-info/top_level.txt
timesheet_gitlab-1.0.1.dist-info/RECORD
